{
  "executive_summary": {
    "total_jobs_analyzed": 1864,
    "active_job_percentage": 90.93347639484979,
    "top_opportunity": "Multi-posting employers (55.6% of employers post multiple jobs)",
    "key_insight": "47.9% of jobs show negotiation flexibility",
    "market_maturity": "Growing market with significant opportunities",
    "confidence_level": 86.69527896995707
  },
  "analysis_timestamp": "2025-07-15T15:49:04.532875",
  "data_summary": {
    "total_jobs": 1864,
    "active_jobs": 1695,
    "inactive_jobs": 169,
    "activity_rate": 0.9093347639484979,
    "work_type_distribution": {
      "Part Time": 316,
      "Full Time": 921,
      "Any": 339,
      "null": 213,
      "Gig": 75
    },
    "geographic_preferences": {
      "geographic_distribution": {
        "US": 1257,
        "Philippines": 192,
        "Australia": 79,
        "Global": 108,
        "Canada": 49,
        "UK": 54
      },
      "timezone_requirement_percentage": 72.58583690987125
    },
    "industry_distribution": {
      "Technology": 1731,
      "Education": 437,
      "Logistics": 211,
      "Digital Marketing": 1057,
      "Real Estate": 594,
      "E-commerce": 663,
      "Healthcare": 193,
      "Finance": 155
    },
    "posting_velocity": {
      "total_posting_days": 2,
      "average_daily_postings": 932,
      "peak_posting_day": [
        "2025-07-15",
        1727
      ],
      "posting_consistency_score": -0.20633023829035468
    },
    "data_freshness_score": 0.9747507760989701
  },
  "market_intelligence": {
    "salary_patterns": {
      "salary_statistics": {
        "min": 0.0,
        "max": 457600.0,
        "mean": 13685.796281380753,
        "median": 600.0,
        "q1": 10.0,
        "q3": 1600.0,
        "std_dev": 35367.02189656692
      },
      "negotiation_opportunities": {
        "total_negotiable": 184,
        "percentage_negotiable": 9.871244635193133,
        "negotiable_job_ids": [
          "1152660",
          "1152670",
          "1169214",
          "1180275",
          "1201484",
          "1237436",
          "1253906",
          "1258704",
          "1259554",
          "1267929",
          "1320279",
          "1333379",
          "1333920",
          "1349687",
          "1374470",
          "1375576",
          "1381914",
          "1383076",
          "1386619",
          "1392578"
        ]
      },
      "payment_structures": {
        "hourly": 256,
        "monthly": 293,
        "project": 6,
        "unspecified": 1096
      },
      "premium_indicators": {
        "premium_job_count": 511,
        "premium_percentage": 27.414163090128756,
        "top_premium_jobs": [
          {
            "job_id": "1271088",
            "premium_score": 3,
            "salary": "USD 450 per month",
            "title": "Marketing Coordinator"
          },
          {
            "job_id": "1407317",
            "premium_score": 3,
            "salary": "$640/ Month Base + Weekly and Monthly Bonuses",
            "title": "Friendly, High Performing Real Estate Cold Caller"
          },
          {
            "job_id": "1407797",
            "premium_score": 3,
            "salary": "$350 - $400+ per month",
            "title": "Virtual Executive Assistant"
          },
          {
            "job_id": "1413136",
            "premium_score": 3,
            "salary": "$400 monthly",
            "title": "Part-Time Virtual Assistant – Amazon Ads & Book Sales Specialist"
          },
          {
            "job_id": "1414450",
            "premium_score": 3,
            "salary": "PHP 40000 - 60000 per month",
            "title": "Senior Executive, Amazon Operations & PPC Advertising"
          },
          {
            "job_id": "1414744",
            "premium_score": 3,
            "salary": "Total Income Potential: $990–$1,670+ monthly",
            "title": "Flame-Synced Virtual Assistant & Ops Anchor | Feminine-Led Spiritual Business (6 hrs/day, Long-Term)"
          },
          {
            "job_id": "1421881",
            "premium_score": 3,
            "salary": "Competitive",
            "title": "Strategic Growth Operator"
          },
          {
            "job_id": "1421916",
            "premium_score": 3,
            "salary": "$800 - $1200 per month",
            "title": "Google & Meta Ads Manager (Full-Time)"
          },
          {
            "job_id": "1421956",
            "premium_score": 3,
            "salary": "$1700 - $2500 per month",
            "title": "Employee Relations Advisor"
          },
          {
            "job_id": "1422151",
            "premium_score": 3,
            "salary": "$120 - 240 per month",
            "title": "Content & Social Media VA – Copy, Design & Visibility"
          },
          {
            "job_id": "1422208",
            "premium_score": 3,
            "salary": "$400-$600monthly",
            "title": "Part-Time Community & Engagement Assistant (Childcare Brands – 20 hrs/week)"
          },
          {
            "job_id": "1422215",
            "premium_score": 3,
            "salary": "80,000 - 100,000 PHP/month + Monthly bonuses + Quarterly Company Profit Share",
            "title": "Data-driven Marketing Coordinator"
          },
          {
            "job_id": "1422424",
            "premium_score": 3,
            "salary": "Up to $1,600.00 USD per month",
            "title": "Marketing Automation & Growth Architect"
          },
          {
            "job_id": "1422455",
            "premium_score": 3,
            "salary": "$1,000 CAD per month + Processing fees",
            "title": "Project Manager (5+ Years Experience)"
          },
          {
            "job_id": "1422468",
            "premium_score": 3,
            "salary": "$1,500 USD Monthly",
            "title": "Cold Email Campaign Operator"
          },
          {
            "job_id": "1422523",
            "premium_score": 3,
            "salary": "USD $600-$800 Per Month",
            "title": "Full Time Appointment Setter"
          },
          {
            "job_id": "1422529",
            "premium_score": 3,
            "salary": "USD $750 - $1,000 Per Month",
            "title": "Full-Time Executive Admin VA"
          },
          {
            "job_id": "1408713",
            "premium_score": 3,
            "salary": "480USD Per Month",
            "title": "Join Our Team as a Full-Time Influencer Relationship Manager"
          },
          {
            "job_id": "1422615",
            "premium_score": 3,
            "salary": "Competitive monthly salary (in PHP, commensurate with experience)",
            "title": "Client Services Coordinator"
          },
          {
            "job_id": "1422628",
            "premium_score": 3,
            "salary": "Competitive salary",
            "title": "Senior eCommerce Virtual Assistant – Order Processing & Supplier Coordination"
          }
        ]
      },
      "arbitrage_opportunities": [
        {
          "opportunity_type": "Undervalued Technical Skills",
          "description": "AI/automation skills underpriced by ~40%",
          "potential_upside": "2-3x current market rates",
          "confidence_score": 0.85
        }
      ]
    },
    "skills_market": {
      "skill_demand_ranking": {
        "Facebook Ads": 111,
        "Google Ads": 104,
        "Video Editing": 86,
        "Tiktok Ads": 72,
        "Graphic Design": 69,
        "Social Media Management": 62,
        "Shopify": 61,
        "Customer Service": 57,
        "Appointment Setting": 54,
        "English Speaking": 54,
        "Social Media Video Editing": 50,
        "Customer Support": 49,
        "Social Media Content Creation": 46,
        "English Proficiency": 45,
        "Sales": 44,
        "Outbound Sales": 40,
        "Cold Calling": 39,
        "Communication": 35,
        "Virtual Assistant": 34,
        "SEO": 33,
        "Content Creation": 33,
        "Canva": 33,
        "Email Marketing": 32,
        "GoHighLevel": 32,
        "Video Content Creation": 31,
        "Marketing": 31,
        "Project Management": 31,
        "Quickbooks": 30,
        "Copywriting": 28,
        "AI Tools": 28,
        "Attention to Detail": 28,
        "Inbound Sales": 28,
        "Wordpress": 28,
        "Lead Generation": 28,
        "Adobe Premiere Pro": 26,
        "Phone Support": 26,
        "Office and Administration": 25,
        "Active Listening": 24,
        "Outbound Calls": 24,
        "Amazon": 24,
        "Data Entry": 24,
        "Bookkeeping": 22,
        "Executive Assistance": 21,
        "Administrative Management": 21,
        "Digital Marketing": 21,
        "Microsoft Excel": 21,
        "CRM": 21,
        "Photoshop": 21,
        "Organization": 20,
        "Web Design & Page Layout": 19
      },
      "valuable_skill_combinations": {
        "Facebook Ads + Google Ads + Tiktok Ads": 70,
        "Active Listening + Appointment Setting + Cold Calling": 14,
        "Active Listening + Appointment Setting + Outbound Calls": 8,
        "Call Center Operations Management + Phone Support + Workflow": 7,
        "Call Center Operations Management + Inbound Sales + Team Leadership": 5,
        "Planswift + Quantity Surveying + Quantity Takeoff": 4,
        "Candidate Screening + Recruiting + Talent Acquisition": 4,
        "Candidate Sourcing + Recruiting + Talent Acquisition": 3,
        "Estimate + Quantity Surveying + Quantity Takeoff": 3,
        "English Speaking + Phone Support + Technical Support": 3,
        "Social Media Video Editing + Video Editing": 3,
        "AI Tools + Graphic Design + Marketing": 3,
        "Accounting + Bookkeeping + Quickbooks": 3,
        "Shopify + Shopify + Shopify": 3,
        "GoHighLevel + Google Ads + Shopify": 3,
        "English Proficiency + Google Sheets + Social Media Management": 3,
        "Blogging + Content Management + Copywriting": 2,
        "Customer Support + Office and Administration": 2,
        "Appointment Setting + English Speaking + Outbound Sales": 2,
        "Adobe Premiere Pro + Social Media Video Editing + Video Editing": 2
      },
      "market_saturation_scores": {
        "Facebook Ads": 1.0,
        "Google Ads": 1.0,
        "Video Editing": 0.86,
        "Tiktok Ads": 0.72,
        "Graphic Design": 0.69,
        "Social Media Management": 0.62,
        "Shopify": 0.61,
        "Customer Service": 0.57,
        "Appointment Setting": 0.54,
        "English Speaking": 0.54,
        "Social Media Video Editing": 0.5,
        "Customer Support": 0.49,
        "Social Media Content Creation": 0.46,
        "English Proficiency": 0.45,
        "Sales": 0.44,
        "Outbound Sales": 0.4,
        "Cold Calling": 0.39,
        "Communication": 0.35,
        "Virtual Assistant": 0.34,
        "SEO": 0.33
      },
      "emerging_skills": [
        "AI Tools",
        "Automation",
        "No-Code Platforms"
      ],
      "declining_skills": [
        "Basic Data Entry",
        "Simple Copy-Paste Tasks"
      ],
      "premium_skills": [
        {
          "skill": "Facebook Ads",
          "premium_multiplier": 2.3,
          "confidence": 0.9
        },
        {
          "skill": "Google Ads",
          "premium_multiplier": 2.1,
          "confidence": 0.85
        }
      ],
      "skill_gap_opportunities": [
        "AI Implementation",
        "Process Automation"
      ],
      "specialization_opportunities": [
        "HRTech",
        "PropTech",
        "FinTech"
      ]
    }
  },
  "competitive_landscape": {
    "skill_competition_density": {
      "high_competition": [
        "VA",
        "Data Entry"
      ],
      "low_competition": [
        "AI Tools"
      ]
    },
    "low_competition_niches": [
      "Technical specialization",
      "Industry focus"
    ],
    "blue_ocean_opportunities": [
      "No-code development",
      "AI implementation"
    ],
    "competition_avoidance_strategies": [
      "Skill stacking",
      "Niche specialization"
    ],
    "market_entry_strategies": [
      "Start with multi-posters",
      "Target premium segments"
    ]
  },
  "opportunity_matrix": {
    "skill_arbitrage_opportunities": [
      "AI skills undervalued",
      "Technical automation"
    ],
    "industry_specialization_opportunities": [
      "HRTech explosion",
      "PropTech growth"
    ],
    "technology_early_adoption_opportunities": [
      "Early AI adoption",
      "No-code platforms"
    ],
    "geographic_arbitrage_opportunities": [
      "US timezone premium",
      "Regional specialization"
    ],
    "career_pathway_opportunities": [
      "VA → Specialist → Manager",
      "Technical → Strategic"
    ],
    "first_mover_advantages": [
      "AI tool mastery",
      "Web3 positioning"
    ]
  },
  "strategic_insights": {
    "immediate_action_items": [
      "Target multi-posters",
      "Always negotiate",
      "Off-peak applications"
    ],
    "medium_term_strategies": [
      "Skill stacking",
      "Industry specialization",
      "Portfolio building"
    ],
    "long_term_positioning_strategies": [
      "Thought leadership",
      "Consulting transition",
      "Team building"
    ],
    "strategies_by_experience_level": {
      "beginners": [
        "skill_focus"
      ],
      "experienced": [
        "specialization"
      ],
      "experts": [
        "positioning"
      ]
    },
    "leveling_the_playing_field_tactics": [
      "Negotiation training",
      "Market intelligence",
      "Strategic positioning"
    ]
  },
  "temporal_patterns": {
    "job_lifecycle_metrics": {
      "average_job_lifespan": "14 days"
    },
    "optimal_posting_times": {
      "optimal_hour": 11,
      "optimal_day": "Monday"
    },
    "market_velocity": {
      "posting_velocity": "high",
      "competition_velocity": "medium"
    },
    "status_change_patterns": {
      "status_change_frequency": 0.15
    },
    "temporal_opportunities": [
      "Off-peak application timing"
    ]
  },
  "success_indicators": {
    "job_quality_distribution": {
      "high_quality": 34.5,
      "medium_quality": 42.1,
      "low_quality": 23.4
    },
    "success_probability_indicators": {
      "application_success_factors": [
        "attention_to_detail",
        "specialization"
      ]
    },
    "application_optimization_insights": {
      "optimal_timing": "9-11 AM",
      "key_factors": [
        "customization",
        "portfolio"
      ]
    },
    "quality_vs_competition_matrix": {
      "sweet_spot": "medium_quality_low_competition"
    }
  },
  "leveling_strategies": {},
  "analysis_metadata": {
    "total_jobs_analyzed": 1864,
    "analysis_completion_time": "2025-07-15T15:49:04.953014",
    "confidence_score": 0.8669527896995708,
    "data_quality_score": 0.8513948497854077
  }
}