{
  "job_id": "1421979",
  "url": "https://www.onlinejobs.ph/jobseekers/job/Video-Editor-Content-Creator-1421979",
  "scraped_at": "2025-07-15T02:30:26.034346",
  "title": "Video Editor - Content Creator",
  "type_of_work": "Part Time",
  "salary": "500$",
  "hours_per_week": "24",
  "date_updated": "Jul 14, 2025",
  "job_overview": "Part-Time Remote Video Editor & Content Creator\n\r\nWe’re looking for a proactive and creative Video Editor & Content Creator to join our team part-time and remotely. If you love editing videos and adding that special touch that makes them stand out, this is the role for you!\n\r\n? What You’ll Do:\n\r\n- Edit and refine video content with Adobe Premiere Pro\r\n- Create simple motion graphics and effects using After Effects\r\n- Collaborate with the team to deliver high-quality video content. \r\n- Take initiative and suggest ideas to improve video output\n\r\n????? Requirements:\n\r\n-Fluent in English\r\n-Excellent knowledge of Adobe Premiere Pro\r\n-Good knowledge of After Effects\r\n-Creative, resourceful, and ready to take on new challenges\r\n-Available to work during 9 AM – 5 PM Copenhagen time\n\r\n? Hiring Test:\r\n Shortlisted candidates will be asked to complete a short test:\r\n- Cut a short section of a video to create a Reel in 9:16 format\r\n- Add creative subtitles to 1 Reel, following the style we’ll share as an example\n\r\n???? What We Offer:\n\r\n- Part-time position: 3 days per week\r\n- Remote work\r\n- $500 USD per month\n\r\n???? How to Apply:\r\nPlease send us your CV and a portfolio with examples of your video editing work. \r\nWe look forward to seeing what you can do!",
  "skill_requirements": [
    "After Effects",
    "Video Editing",
    "Adobe Premiere Pro"
  ],
  "is_active": true,
  "status_history": []
}