{
  "job_id": "1422304",
  "url": "https://www.onlinejobs.ph/jobseekers/job/Amazon-FBAFBM-Product-Research-VA-Part-Time-Keepa-SellerAmp-Required-34hr-1422304",
  "scraped_at": "2025-07-14T23:09:22.155764",
  "title": "Amazon FBA/FBM Product Research VA – Part-Time | Keepa + SellerAmp Required | $3–$4/hr",
  "type_of_work": "Part Time",
  "salary": "80",
  "hours_per_week": "5",
  "date_updated": "Jul 14, 2025",
  "job_overview": "Are you an experienced Amazon FBA Product Research VA looking for a flexible, part-time role with long-term potential? I'm a U.S.-based Amazon seller searching for someone who can deliver 10- 15 high-quality, profitable leads per week using Keepa and SellerAmp (SAS).\n\r\nThis is a performance-based position with steady, part-time hours. If you're detail-oriented, dependable, and already trained in online arbitrage sourcing, this could be the perfect role for you.",
  "skill_requirements": [
    "FBA",
    "Online Arbitrage",
    "Seller Amp SAS"
  ]
}