{
  "job_id": "1422859",
  "url": "https://www.onlinejobs.ph/jobseekers/job/Social-Media-Content-Manager-Part-Time-1422859",
  "scraped_at": "2025-07-15T12:23:48.820294",
  "title": "Social Media / Content Manager (Part-Time)",
  "type_of_work": "Part Time",
  "salary": "18,000",
  "hours_per_week": "20",
  "date_updated": "Jul 15, 2025",
  "job_overview": "???? HIRING: Social Media / Content Manager (Part-Time, Remote, Philippines)\r\n???? 20 hours per week | Long-term | Work-from-home\n\r\nWe’re a digital marketing agency in Australia looking for a sharp, proactive Social Media / Content Manager to help handle our clients’ online presence.\n\r\n? What you’ll do:\n\r\nPlan and schedule posts across Facebook & Instagram\n\r\nWrite engaging captions & research relevant hashtags\n\r\nReply to comments & DMs in a friendly, professional tone\n\r\nStay updated on local trends, competitor pages & new features\n\r\nSet up and track simple boosted posts / ad campaigns\n\r\nReport on engagement & growth monthly\n\r\n???? Who we’re looking for:\n\r\nStrong written English (friendly, witty, professional)\n\r\nSocial media savvy — knows reels, carousels, trends, Upgrade to see actual infos\n\r\nExperience with Canva, Facebook Creator Studio, Meta Business Suite\n\r\nProactive — can take a brief and run with it\n\r\nOrganised with content calendars & schedules\n\r\n???? Perks:\n\r\nLong-term role with stable hours (20/week)\n\r\nChance to grow into a full-time position or team lead\n\r\nFriendly, supportive team — we want you to shine\n\r\n???? To apply:\r\nSend us:\n\r\nA quick intro video (30 sec, can be casual!)\n\r\nExamples of pages you’ve managed or content you’ve written\n\r\nYour expected monthly rate for 20 hours/week",
  "skill_requirements": [
    "Facebook marketing",
    "Canva",
    "Meta Business Suite"
  ],
  "is_active": true,
  "status_history": [
    {
      "status": "active",
      "timestamp": "2025-07-15T07:41:26.736712",
      "reason": "Job first discovered"
    }
  ]
}