{
  "job_id": "1422637",
  "url": "https://www.onlinejobs.ph/jobseekers/job/Operation-Assistant-1422637",
  "scraped_at": "2025-07-15T14:27:33.799007",
  "title": "Operation Assistant",
  "type_of_work": "Full Time",
  "salary": "450 - 500",
  "hours_per_week": "40",
  "date_updated": "Jul 15, 2025",
  "job_overview": "Job brief\r\nWe are looking for a responsible Personal Assistant to provide operation support in a well-organized and timely manner. You will work on a one-to-one basis on a variety of tasks related to manager’s daily operation task.\n\r\nJob Duty\r\n· preparing reports, presentations and correspondence\n\r\n· preparing any research that the reporting manager may require\n\r\n· assisting ecommerce relative tasks (including but not limit to: replying message, Processing orders, Listing, Download & Upload file, audit current listing, and etc.)\n\r\n· any other operation relative matters\n\r\nRequirement\n\r\n· Proficient with Microsoft Excel - Must\n\r\n· Proficient with Business Math - Must\n\r\n· Fluent in English - Must\n\r\n· Two monitors -Prefer\n\r\n· Excellent oral and written communication skills - Must\n\r\n· Strong organizational skills and the ability to multitask - Must\n\r\n· College / Bachelor degree – Preferred\n\r\nOur company is located in East Coast, USA. Our office hour is 8:30am to 5:30pm EST USA",
  "skill_requirements": [
    "Microsoft Excel",
    "Attention to Detail",
    "Organization"
  ],
  "is_active": true,
  "status_history": [
    {
      "status": "active",
      "timestamp": "2025-07-15T01:31:31.430359",
      "reason": "Job first discovered"
    }
  ]
}