{
  "job_id": "1422103",
  "url": "https://www.onlinejobs.ph/jobseekers/job/Executive-Assistant-US-Technical-Recruitment-1422103",
  "scraped_at": "2025-07-15T12:01:56.304651",
  "title": "Executive Assistant | US Technical Recruitment",
  "type_of_work": "Part Time",
  "salary": "700 USD per month (part-time)",
  "hours_per_week": "20",
  "date_updated": "Jul 14, 2025",
  "job_overview": "Role Description:\n\r\nDay-to-day tasks include scheduling meetings, maintaining calendars, filing and management, personal support, and assisting with recruitment processes (which involves interviews, sourcing, and screening). The role requires excellent organizational skills, ability to handle confidential information, learn things fast, and be attentive to details.\n\r\nThis position will more likely to transition to a full-time role.\n\r\nWhat You’ll Bring:\n\r\n- 2+ years as a virtual Executive Assistant for an international client, or similar role\r\n- US software technical recruitment experience\r\n- Hiring experience for US tech government role is a huge plus\r\n- Exceptional written and verbal communication skills\r\n- Process-driven approach with a knack for continuous improvement\r\n- High degree of client care and professionalism",
  "skill_requirements": [
    "US recruiting",
    "Technical recruiting",
    "Executive Assistance"
  ],
  "is_active": true,
  "status_history": []
}