{
  "job_id": "1422992",
  "url": "https://www.onlinejobs.ph/jobseekers/job/Digital-Content-Reviewer-WFH-PHP-15K-30K-1422992",
  "scraped_at": "2025-07-15T14:40:56.053208",
  "title": "Digital Content Reviewer – WFH (PHP 15K – 30K!)",
  "type_of_work": "Any",
  "salary": "15000 to 150000",
  "hours_per_week": "TBD",
  "date_updated": "Jul 15, 2025",
  "job_overview": "Easy Online Job – No Experience Needed!\n\r\nWe’re hiring Digital Content Reviewers to check posts, ads, and videos—WFH, flexible hours! Perfect for students, moms, or anyone who wants easy online income!\n\r\n? Job Tasks:\n\r\nReview social media posts, ads, or videos for guidelines\n\r\nFlag inappropriate content & submit reports\n\r\nBasic data entry & logging\n\r\n? Requirements:\n\r\nBasic computer/mobile skills (you know how to browse!)\n\r\nCan commit 5 mins every 20 mins\n\r\nNo experience? Training provided!\n\r\n???? Earn PHP 15,000 – 30,000/month + bonuses!\r\n? Flexible shifts – Work anytime!\r\n???? Apply now—start next week!                \n\n\n\n\n\n\n\nVIEW OTHER JOB POSTS FROM:\n\n\n\n\n\n\n\nSHARE THIS POST\n\n\n\n\n\n\n\n\n\n\n\n\nReport\n\n×\n\n\n\n\n\n\nJob Post\nReporter\nRank\nReason\n\n\n\n\n\n\n\n\n\n\n\n\n\n\n\n\nBookmark Note:\n\n×\n\n\n\n\n\n\n\n\n\n\n\n\n\n\n\n\n\n\n\n\n\n\n\n\n\n\nWhy is this blurred?\n\n                            For privacy and security reasons, you need to be logged into an OnlineJobs.ph account in order to view this link.\n                        \n        \n\n\n\n\n\n\n\n\n\nEmployers\n\n\n\nHow it works\nRegister\nPost a Job\nBlog\nReal Results\nFAQ\nTimeproof\n\n\n\n\n\nWorkers\n\n\n\nHow it works\nRegister\nJob Search\nEmployer Search\nBehind the Screen\n\n\n\n\n\ntalented va's\n\n\n\nVirtual Assistant\nSEO Experts\nWordPress Experts\nSocial Media Managers\nVideo Editors \nReal Estate Experts\nArticle Writers\nAmazon Experts\nGraphic Designers\nShopify Experts\nAdvanced VA Search\n\n\n\n\n\nother goods\n\n\n\nPress\nAffiliates\nAbout Us\nContact Us\nPrivacy Policy\nTerms of Use\nSPREAD THE WORD\n\n\n\n\n\ncontact us\n\n\n\n support@onlinejobs.ph\n\n\n\n\n\nconnect with us\n\n\n\n\n\n\n\n\n\n\n\n\n\n\n\n\n\n\n\n\nCopyright © 2025 OnlineJobs.ph. All rights reserved.\nCopyright © 2025 OnlineJobs.ph. All rights reserved.\n\n\n\n\n\n\n\n\n\n\n \n\nQuestions? Feedback?powered byOlark live chat software",
  "skill_requirements": [],
  "is_active": true,
  "status_history": [
    {
      "status": "active",
      "timestamp": "2025-07-15T10:19:58.046594",
      "reason": "Job first discovered"
    }
  ]
}