{
  "job_id": "1422441",
  "url": "https://www.onlinejobs.ph/jobseekers/job/Customer-Service-Representative-1422441",
  "scraped_at": "2025-07-14T23:07:53.501084",
  "title": "Customer Service Representative",
  "type_of_work": "Full Time",
  "salary": "N/A",
  "hours_per_week": "40",
  "date_updated": "Jul 14, 2025",
  "job_overview": "Join Our Team at Atticare!\r\nWe’re a fast-growing home service company specializing in insulation, wildlife removal, rodent exclusion, and pest control. With a strong reputation for quality work and top-notch service, we’re looking for a Customer Service Representative who’s ready to make a real impact on our customers' lives and homes.\n\r\nWhat You'll Do:\n\r\nBe the friendly voice that customers hear first—answering calls, emails, and online inquiries\r\nSchedule inspections and service appointments with accuracy and efficiency\r\nProvide knowledgeable support on our services and guide customers through their options\r\nDispatch technicians and coordinate routes based on urgency, availability, and location\r\nFollow up on leads, estimates, and open tickets to ensure smooth service delivery\r\nInput and update customer data in our CRM system\r\nHandle complaints or concerns with professionalism and empathy\r\nCollaborate with sales and field teams to provide a seamless customer experience\r\nWhat We're Looking For:\n\r\nStrong communication and interpersonal skills\r\nExperience in a customer service, call center, or dispatching role (home services industry is a plus)\r\nAbility to multitask and stay organized in a fast-paced environment\r\nTech-savvy with experience using Google Workspace, CRM systems, and scheduling tools\r\nPositive attitude and a genuine desire to help people\r\nBilingual (English/Spanish) is a bonus",
  "skill_requirements": [
    "Customer Support",
    "Professional Services"
  ]
}