{
  "job_id": "1422319",
  "url": "https://www.onlinejobs.ph/jobseekers/job/Commercial-Cleaning-Appointment-Setter-1422319",
  "scraped_at": "2025-07-15T12:24:48.947779",
  "title": "Commercial Cleaning Appointment Setter",
  "type_of_work": "Gig",
  "salary": "$400",
  "hours_per_week": "40",
  "date_updated": "Jul 14, 2025",
  "job_overview": "We are looking for a skilled and reliable Appointment Setter to help schedule walkthroughs for commercial cleaning services. You'll be responsible for cold calling local businesses, introducing our services, and booking on-site appointments (walkthroughs) for quotes.\n\r\nPay: $2.50 per hour + $50 per qualified appointment set (must be confirmed by the business and result in an on-site walkthrough).\n\r\nRequirements: Fluent in English with clear, professional phone presence\n\r\nExperience in appointment setting or cold calling\n\r\nMust be comfortable calling business owners, office managers, and facility managers\n\r\nAble to use a provided script and CRM to log activity\n\r\nMust be available during U.S. business hours (your choice of timezone)\n\r\nQuiet work environment and high-speed internet\n\r\nWhat We Provide:\n\r\nDialer and phone system access\n\r\nTargeted call lists (local businesses in specific areas)\n\r\nScripts and objection handling guides\n\r\nTraining and ongoing support\n\r\nAbout Us:\r\nWe work with commercial cleaning companies across the U.S. and help them grow by setting up on-site walkthroughs with office buildings, schools, medical facilities, warehouses, and more.\n\r\nOnly apply if you're confident in your ability to get decision-makers on the phone and book real appointments.",
  "skill_requirements": [
    "Cold Calling",
    "Appointment Setting"
  ],
  "is_active": true,
  "status_history": []
}